ichigo_asr/__init__.py
ichigo_asr/config/__init__.py
ichigo_asr/config/trainer_config.py
ichigo_asr/config/vq_config.py
ichigo_asr/data/__init__.py
ichigo_asr/data/dataset.py
ichigo_asr/data/hf.py
ichigo_asr/data/utils.py
ichigo_asr/data/process_data/concat_dataset.py
ichigo_asr/data/process_data/process_gigas.py
ichigo_asr/data/process_data/process_gt.py
ichigo_asr/data/process_data/split_data.py
ichigo_asr/data/process_data/transcribe_dataset.py
ichigo_asr/demo/__init__.py
ichigo_asr/demo/app.py
ichigo_asr/demo/inference.py
ichigo_asr/demo/utils.py
ichigo_asr/demo/samples/test.wav
ichigo_asr/models/__init__.py
ichigo_asr/models/factory.py
ichigo_asr/models/layers.py
ichigo_asr/models/modules.py
ichigo_asr/models/vq_transformer.py
ichigo_asr/scripts/concat_data.sh
ichigo_asr/scripts/test.py
ichigo_asr/scripts/test.sh
ichigo_asr/scripts/train.py
ichigo_asr/scripts/train_multi.sh
ichigo_asr/scripts/train_single.sh
ichigo_asr/trainer/__init__.py
ichigo_asr/trainer/lightning_module.py
ichigo_asr/trainer/trainer.py
ichigo_asr/trainer/utils.py
ichigo_asr/utils/data_eda.ipynb
ichigo_asr/utils/token_viz.ipynb
ichigo_asr/utils/data/libritts - merge 7lang - 512 last - p2 5e.csv
ichigo_asr/utils/data/vivoice - merge 7lang - 512 last - p2 5e.csv
ichigo_asr-0.1.1.dist-info/METADATA
ichigo_asr-0.1.1.dist-info/WHEEL
ichigo_asr-0.1.1.dist-info/top_level.txt
ichigo_asr-0.1.1.dist-info/RECORD
